pix2text/__init__.py
pix2text/__version__.py
pix2text/app.py
pix2text/cli.py
pix2text/consts.py
pix2text/doc_yolo_layout_parser.py
pix2text/formula_detector.py
pix2text/latex_ocr.py
pix2text/layout_parser.py
pix2text/ocr_engine.py
pix2text/page_elements.py
pix2text/pix_to_text.py
pix2text/render.py
pix2text/screenshot_daemon_with_server2.py
pix2text/serve.py
pix2text/table_inference.py
pix2text/table_ocr.py
pix2text/table_postprocess.py
pix2text/text_formula_ocr.py
pix2text/utils.py
pix2text/vlm_api.py
pix2text/vlm_table_ocr.py
pix2text/doc_xl_layout/__init__.py
pix2text/doc_xl_layout/doc_xl_layout_parser.py
pix2text/doc_xl_layout/huntie_subfield.py
pix2text/doc_xl_layout/opts.py
pix2text/doc_xl_layout/wrapper.py
pix2text/doc_xl_layout/detectors/__init__.py
pix2text/doc_xl_layout/detectors/base_detector_subfield.py
pix2text/doc_xl_layout/detectors/ctdet_subfield.py
pix2text/doc_xl_layout/detectors/detector_factory.py
pix2text/doc_xl_layout/external/__init__.py
pix2text/doc_xl_layout/external/shapelyNMS.py
pix2text/doc_xl_layout/models/__init__.py
pix2text/doc_xl_layout/models/data_parallel.py
pix2text/doc_xl_layout/models/decode.py
pix2text/doc_xl_layout/models/model.py
pix2text/doc_xl_layout/models/scatter_gather.py
pix2text/doc_xl_layout/models/utils.py
pix2text/doc_xl_layout/models/networks/__init__.py
pix2text/doc_xl_layout/models/networks/dlav0_subfield.py
pix2text/doc_xl_layout/utils/__init__.py
pix2text/doc_xl_layout/utils/ddd_utils.py
pix2text/doc_xl_layout/utils/debugger.py
pix2text/doc_xl_layout/utils/evaluation_bk.py
pix2text/doc_xl_layout/utils/image.py
pix2text/doc_xl_layout/utils/post_process.py
pix2text/doc_xl_layout/utils/utils.py
pix2text/layoutlmv3/__init__.py
pix2text/layoutlmv3/backbone.py
pix2text/layoutlmv3/beit.py
pix2text/layoutlmv3/deit.py
pix2text/layoutlmv3/layoutlmv3_layout_parser.py
pix2text/layoutlmv3/rcnn_vl.py
pix2text/layoutlmv3/visualizer.py
pix2text/layoutlmv3/layoutlmft/__init__.py
pix2text/layoutlmv3/layoutlmft/data/__init__.py
pix2text-1.1.4.dist-info/LICENSE
pix2text-1.1.4.dist-info/METADATA
pix2text-1.1.4.dist-info/WHEEL
pix2text-1.1.4.dist-info/entry_points.txt
pix2text-1.1.4.dist-info/top_level.txt
pix2text-1.1.4.dist-info/RECORD
