Metadata-Version: 2.1
Name: pix2text
Version: 1.1.4
Summary: An Open-Source Python3 tool for recognizing layouts, tables, math formulas, and text in images, converting them into Markdown format. A free alternative to Mathpix, empowering seamless conversion of visual content into text-based representations.
Home-page: https://github.com/breezedeus/pix2text
Author: breezedeus
Author-email: breezedeus@163.com
License: MIT
Platform: Mac
Platform: Linux
Platform: Windows
Classifier: Development Status :: 4 - Beta
Classifier: Operating System :: OS Independent
Classifier: Intended Audience :: Developers
Classifier: License :: OSI Approved :: MIT License
Classifier: Programming Language :: Python
Classifier: Programming Language :: Python :: Implementation
Classifier: Programming Language :: Python :: 3
Classifier: Programming Language :: Python :: 3.8
Classifier: Programming Language :: Python :: 3.9
Classifier: Programming Language :: Python :: 3.10
Classifier: Programming Language :: Python :: 3.11
Classifier: Topic :: Scientific/Engineering :: Artificial Intelligence
License-File: LICENSE
Requires-Dist: click
Requires-Dist: tqdm
Requires-Dist: numpy
Requires-Dist: opencv-python
Requires-Dist: cnocr[ort-cpu]>=2.3.0.2
Requires-Dist: cnstd>=1.2.4.2
Requires-Dist: pillow
Requires-Dist: torch
Requires-Dist: torchvision
Requires-Dist: transformers>=4.37.0
Requires-Dist: optimum[onnxruntime]
Requires-Dist: PyMuPDF
Requires-Dist: pyspellchecker
Requires-Dist: doclayout-yolo<0.1
Provides-Extra: dev
Requires-Dist: pip-tools; extra == "dev"
Requires-Dist: pytest; extra == "dev"
Provides-Extra: multilingual
Requires-Dist: easyocr; extra == "multilingual"
Provides-Extra: serve
Requires-Dist: uvicorn[standard]; extra == "serve"
Requires-Dist: fastapi; extra == "serve"
Requires-Dist: python-multipart; extra == "serve"
Requires-Dist: pydantic; extra == "serve"
Provides-Extra: vlm
Requires-Dist: litellm; extra == "vlm"
